drfpasswordless/__init__.py
drfpasswordless/__version__.py
drfpasswordless/admin.py
drfpasswordless/apps.py
drfpasswordless/models.py
drfpasswordless/serializers.py
drfpasswordless/services.py
drfpasswordless/settings.py
drfpasswordless/signals.py
drfpasswordless/urls.py
drfpasswordless/utils.py
drfpasswordless/views.py
drfpasswordless/migrations/0001_initial.py
drfpasswordless/migrations/0002_auto_20200122_0424.py
drfpasswordless/migrations/0003_callbacktoken_type.py
drfpasswordless/migrations/0004_auto_20200125_0853.py
drfpasswordless/migrations/0005_auto_20201117_0410.py
drfpasswordless/migrations/__init__.py
drfpasswordless/templates/passwordless_default_token_email.html
drfpasswordless/templates/passwordless_default_verification_token_email.html
drfpasswordless_decho_fork-1.5.8.dist-info/LICENSE
drfpasswordless_decho_fork-1.5.8.dist-info/METADATA
drfpasswordless_decho_fork-1.5.8.dist-info/WHEEL
drfpasswordless_decho_fork-1.5.8.dist-info/top_level.txt
drfpasswordless_decho_fork-1.5.8.dist-info/RECORD
